integrate_BSSD_into_OpenDRIVE/__init__.py
integrate_BSSD_into_OpenDRIVE/__main__.py
integrate_BSSD_into_OpenDRIVE/algorithms/A_1_find_drivable_lanes.py
integrate_BSSD_into_OpenDRIVE/algorithms/A_2_manually_edit_drivable_lanes.py
integrate_BSSD_into_OpenDRIVE/algorithms/A_3_1_segments_by_changing_number_of_drivable_lanes.py
integrate_BSSD_into_OpenDRIVE/algorithms/A_3_2_segments_by_starting_and_ending_drivable_lanes.py
integrate_BSSD_into_OpenDRIVE/algorithms/A_3_3_segments_by_speed_limit.py
integrate_BSSD_into_OpenDRIVE/algorithms/A_3_4_segments_by_static_signals.py
integrate_BSSD_into_OpenDRIVE/algorithms/A_3_5_segments_by_dynamic_signals.py
integrate_BSSD_into_OpenDRIVE/algorithms/A_3_extract_segments_automatically.py
integrate_BSSD_into_OpenDRIVE/algorithms/A_4_manually_edit_segments.py
integrate_BSSD_into_OpenDRIVE/algorithms/A_5_find_overlappings_segments_laneSections.py
integrate_BSSD_into_OpenDRIVE/algorithms/A_6_search_linked_OpenDRIVE_lanes.py
integrate_BSSD_into_OpenDRIVE/algorithms/A_7_1_extract_speed_attribute.py
integrate_BSSD_into_OpenDRIVE/algorithms/A_7_extract_behavioral_attributes_automatically.py
integrate_BSSD_into_OpenDRIVE/concept_steps/step_1_import_and_validate_xodr.py
integrate_BSSD_into_OpenDRIVE/concept_steps/step_2_create_BSSD_root_elements.py
integrate_BSSD_into_OpenDRIVE/concept_steps/step_3_create_BSSD_segments.py
integrate_BSSD_into_OpenDRIVE/concept_steps/step_4_create_BSSD_lane_groups.py
integrate_BSSD_into_OpenDRIVE/concept_steps/step_5_create_BSSD_lanes.py
integrate_BSSD_into_OpenDRIVE/concept_steps/step_6_link_BSSD_and_OpenDRIVE_lanes.py
integrate_BSSD_into_OpenDRIVE/concept_steps/step_7_create_minimal_behavior_space_structure.py
integrate_BSSD_into_OpenDRIVE/concept_steps/step_8_fill_BSSD_behavioral_attributes.py
integrate_BSSD_into_OpenDRIVE/concept_steps/step_9_save_modified_xodr.py
integrate_BSSD_into_OpenDRIVE/data/OpenDRIVE_1.4H_Schema_Files.xsd
integrate_BSSD_into_OpenDRIVE/data/OpenDRIVE_1.5_Schema_Files.xsd
opendrive_bssd_converter-2025.1.dist-info/LICENSE
opendrive_bssd_converter-2025.1.dist-info/METADATA
opendrive_bssd_converter-2025.1.dist-info/WHEEL
opendrive_bssd_converter-2025.1.dist-info/entry_points.txt
opendrive_bssd_converter-2025.1.dist-info/top_level.txt
opendrive_bssd_converter-2025.1.dist-info/RECORD
