Metadata-Version: 2.1
Name: opendrive-bssd-converter
Version: 2025.1
Summary: Tool for the automated generation of the BSSD extension based on OpenDRIVE maps
Author-email: "Institute of Automotive Engineering, Technical University of Darmstadt" <open-source@fzd.tu-darmstadt.de>
Maintainer-email: "Institute of Automotive Engineering, Technical University of Darmstadt" <open-source@fzd.tu-darmstadt.de>
License: Copyright 2024 Institute of Automotive Engineering (FZD), Technical University of Darmstadt
Project-URL: BSSD-Homepage, https://gitlab.com/tuda-fzd/scenery-representations-and-maps/behavior-semantic-scenery-description
Project-URL: Repository, https://gitlab.com/tuda-fzd/scenery-representations-and-maps/opendrive-bssd-converter
Keywords: automated driving,BSSD,OpenDRIVE
Classifier: License :: OSI Approved :: MIT License
Classifier: Programming Language :: Python
Classifier: Programming Language :: Python :: 3
Requires-Python: >=3.8
License-File: LICENSE
Requires-Dist: easygui==0.98.1
Requires-Dist: lxml==4.6.3
Requires-Dist: pandas==1.3.4
Requires-Dist: rich==10.16.2
Requires-Dist: scipy==1.7.1
Requires-Dist: tqdm==4.62.3
Requires-Dist: importlib-resources
Provides-Extra: dev
Requires-Dist: pytest; extra == "dev"
